line_buffer.sv
module line_buffer #(parameter WIDTH = 100, parameter DATA_WIDTH = 24) (
    input clk,
    input rst_n,
    input shift_en,
    input [DATA_WIDTH-1:0] data_in,
    output [DATA_WIDTH-1:0] data_out
);

logic [DATA_WIDTH-1:0] arr [WIDTH-1:0];

always_ff @(posedge clk or negedge rst_n) begin
    if(!rst_n) begin
        for(int i = 0; i < WIDTH; i = i+1) begin
            arr[i] <= {DATA_WIDTH{1'b0}};
        end
    end
    else if (shift_en) begin
        arr[0] <= data_in;
        for(int i = 1; i < WIDTH; i = i+1) begin
            arr[i] <= arr[i-1];
        end 
    end
end

assign data_out = arr[WIDTH-1];

endmodule

row_fifo_manager.sv
module row_fifo_manager #(parameter WIDTH = 100, parameter DATA_WIDTH = 8) (
    input clk,
    input rst_n,
    input shift_en,
    input [DATA_WIDTH-1:0] data_in,
    output [DATA_WIDTH-1:0] row0,
    output [DATA_WIDTH-1:0] row1,
    output [DATA_WIDTH-1:0] row2
);

logic [DATA_WIDTH-1:0] lb1_out;
logic [DATA_WIDTH-1:0] lb2_out;

line_buffer #(.WIDTH(WIDTH+1), .DATA_WIDTH(DATA_WIDTH))lb1 (.clk(clk), .rst_n(rst_n), .shift_en(shift_en),
                .data_in(data_in), .data_out(lb1_out));
                
line_buffer #(.WIDTH(WIDTH), .DATA_WIDTH(DATA_WIDTH)) lb2 (.clk(clk), .rst_n(rst_n), .shift_en(shift_en),
                .data_in(lb1_out), .data_out(lb2_out));


assign row2 = data_in;
assign row1 = lb1_out;
assign row0 = lb2_out;

endmodule

tb_row_fifo_manager.sv
`timescale 1ns / 1ps

module tb_row_fifo_manager();

    logic clk;
    logic rst_n;
    logic shift_en;
    logic [23:0] data_in;
    logic [23:0] row0, row1, row2;

    row_fifo_manager #(.WIDTH(100), .DATA_WIDTH(24)) dut (
        .clk(clk),
        .rst_n(rst_n),
        .shift_en(shift_en),
        .data_in(data_in),
        .row0(row0),
        .row1(row1),
        .row2(row2)
    );

    initial clk = 0;
    always #5 clk = ~clk;

    initial begin
        rst_n = 0;
        shift_en = 0;
        data_in = 0;

        #20 rst_n = 1;
        #10 shift_en = 1;
        @(posedge clk);

        for (int i = 1; i <= 350; i = i + 1) begin
            data_in = i;
            @(posedge clk);
        end

        #100 $finish;
    end

    initial begin
        $dumpfile("waves.vcd");
        $dumpvars(0, tb_row_fifo_manager);
    end

endmodule

waves.vcd
$date
	Fri Jan  2 19:29:34 2026
$end
$version
	Icarus Verilog
$end
$timescale
	1ps
$end
$scope module tb_row_fifo_manager $end
$var wire 24 ! row2 [23:0] $end
$var wire 24 " row1 [23:0] $end
$var wire 24 # row0 [23:0] $end
$var reg 1 $ clk $end
$var reg 24 % data_in [23:0] $end
$var reg 1 & rst_n $end
$var reg 1 ' shift_en $end
$scope module dut $end
$var wire 1 $ clk $end
$var wire 24 ( data_in [23:0] $end
$var wire 24 ) lb1_out [23:0] $end
$var wire 24 * lb2_out [23:0] $end
$var wire 24 + row0 [23:0] $end
$var wire 24 , row1 [23:0] $end
$var wire 24 - row2 [23:0] $end
$var wire 1 & rst_n $end
$var wire 1 ' shift_en $end
$var parameter 32 . DATA_WIDTH $end
$var parameter 32 / WIDTH $end
$scope module lb1 $end
$var wire 1 $ clk $end
$var wire 24 0 data_in [23:0] $end
$var wire 24 1 data_out [23:0] $end
$var wire 1 & rst_n $end
$var wire 1 ' shift_en $end
$var parameter 32 2 DATA_WIDTH $end
$var parameter 33 3 WIDTH $end
$scope begin $ivl_for_loop0 $end
$var integer 32 4 i [31:0] $end
$upscope $end
$scope begin $ivl_for_loop1 $end
$var integer 32 5 i [31:0] $end
$upscope $end
$upscope $end
$scope module lb2 $end
$var wire 1 $ clk $end
$var wire 24 6 data_in [23:0] $end
$var wire 24 7 data_out [23:0] $end
$var wire 1 & rst_n $end
$var wire 1 ' shift_en $end
$var parameter 32 8 DATA_WIDTH $end
$var parameter 32 9 WIDTH $end
$scope begin $ivl_for_loop0 $end
$var integer 32 : i [31:0] $end
$upscope $end
$scope begin $ivl_for_loop1 $end
$var integer 32 ; i [31:0] $end
$upscope $end
$upscope $end
$upscope $end
$scope begin $ivl_for_loop2 $end
$var integer 32 < i [31:0] $end
$upscope $end
$upscope $end
$enddefinitions $end
$comment Show the parameter values. $end
$dumpall
b1100100 9
b11000 8
b1100101 3
b11000 2
b1100100 /
b11000 .
$end
#0
$dumpvars
b0 <
b0 ;
b1100100 :
b0 7
b0 6
b0 5
b1100101 4
b0 1
b0 0
b0 -
b0 ,
b0 +
b0 *
b0 )
b0 (
0'
0&
b0 %
0$
b0 #
b0 "
b0 !
$end
#5000
b1100100 :
b1100101 4
1$
#10000
0$
#15000
b1100100 :
b1100101 4
1$
#20000
0$
1&
#25000
1$
#30000
0$
1'
#35000
b1100101 5
b1100100 ;
b1 !
b1 -
b1 %
b1 (
b1 0
b1 <
1$
#40000
0$
#45000
b1100101 5
b1100100 ;
b10 !
b10 -
b10 %
b10 (
b10 0
b10 <
1$
#50000
0$
#55000
b1100101 5
b1100100 ;
b11 !
b11 -
b11 %
b11 (
b11 0
b11 <
1$
#60000
0$
#65000
b1100101 5
b1100100 ;
b100 !
b100 -
b100 %
b100 (
b100 0
b100 <
1$
#70000
0$
#75000
b1100101 5
b1100100 ;
b101 !
b101 -
b101 %
b101 (
b101 0
b101 <
1$
#80000
0$
#85000
b1100101 5
b1100100 ;
b110 !
b110 -
b110 %
b110 (
b110 0
b110 <
1$
#90000
0$
#95000
b1100101 5
b1100100 ;
b111 !
b111 -
b111 %
b111 (
b111 0
b111 <
1$
#100000
0$
#105000
b1100101 5
b1100100 ;
b1000 !
b1000 -
b1000 %
b1000 (
b1000 0
b1000 <
1$
#110000
0$
#115000
b1100101 5
b1100100 ;
b1001 !
b1001 -
b1001 %
b1001 (
b1001 0
b1001 <
1$
#120000
0$
#125000
b1100101 5
b1100100 ;
b1010 !
b1010 -
b1010 %
b1010 (
b1010 0
b1010 <
1$
#130000
0$
#135000
b1100101 5
b1100100 ;
b1011 !
b1011 -
b1011 %
b1011 (
b1011 0
b1011 <
1$
#140000
0$
#145000
b1100101 5
b1100100 ;
b1100 !
b1100 -
b1100 %
b1100 (
b1100 0
b1100 <
1$
#150000
0$
#155000
b1100101 5
b1100100 ;
b1101 !
b1101 -
b1101 %
b1101 (
b1101 0
b1101 <
1$
#160000
0$
#165000
b1100101 5
b1100100 ;
b1110 !
b1110 -
b1110 %
b1110 (
b1110 0
b1110 <
1$
#170000
0$
#175000
b1100101 5
b1100100 ;
b1111 !
b1111 -
b1111 %
b1111 (
b1111 0
b1111 <
1$
#180000
0$
#185000
b1100101 5
b1100100 ;
b10000 !
b10000 -
b10000 %
b10000 (
b10000 0
b10000 <
1$
#190000
0$
#195000
b1100101 5
b1100100 ;
b10001 !
b10001 -
b10001 %
b10001 (
b10001 0
b10001 <
1$
#200000
0$
#205000
b1100101 5
b1100100 ;
b10010 !
b10010 -
b10010 %
b10010 (
b10010 0
b10010 <
1$
#210000
0$
#215000
b1100101 5
b1100100 ;
b10011 !
b10011 -
b10011 %
b10011 (
b10011 0
b10011 <
1$
#220000
0$
#225000
b1100101 5
b1100100 ;
b10100 !
b10100 -
b10100 %
b10100 (
b10100 0
b10100 <
1$
#230000
0$
#235000
b1100101 5
b1100100 ;
b10101 !
b10101 -
b10101 %
b10101 (
b10101 0
b10101 <
1$
#240000
0$
#245000
b1100101 5
b1100100 ;
b10110 !
b10110 -
b10110 %
b10110 (
b10110 0
b10110 <
1$
#250000
0$
#255000
b1100101 5
b1100100 ;
b10111 !
b10111 -
b10111 %
b10111 (
b10111 0
b10111 <
1$
#260000
0$
#265000
b1100101 5
b1100100 ;
b11000 !
b11000 -
b11000 %
b11000 (
b11000 0
b11000 <
1$
#270000
0$
#275000
b1100101 5
b1100100 ;
b11001 !
b11001 -
b11001 %
b11001 (
b11001 0
b11001 <
1$
#280000
0$
#285000
b1100101 5
b1100100 ;
b11010 !
b11010 -
b11010 %
b11010 (
b11010 0
b11010 <
1$
#290000
0$
#295000
b1100101 5
b1100100 ;
b11011 !
b11011 -
b11011 %
b11011 (
b11011 0
b11011 <
1$
#300000
0$
#305000
b1100101 5
b1100100 ;
b11100 !
b11100 -
b11100 %
b11100 (
b11100 0
b11100 <
1$
#310000
0$
#315000
b1100101 5
b1100100 ;
b11101 !
b11101 -
b11101 %
b11101 (
b11101 0
b11101 <
1$
#320000
0$
#325000
b1100101 5
b1100100 ;
b11110 !
b11110 -
b11110 %
b11110 (
b11110 0
b11110 <
1$
#330000
0$
#335000
b1100101 5
b1100100 ;
b11111 !
b11111 -
b11111 %
b11111 (
b11111 0
b11111 <
1$
#340000
0$
#345000
b1100101 5
b1100100 ;
b100000 !
b100000 -
b100000 %
b100000 (
b100000 0
b100000 <
1$
#350000
0$
#355000
b1100101 5
b1100100 ;
b100001 !
b100001 -
b100001 %
b100001 (
b100001 0
b100001 <
1$
#360000
0$
#365000
b1100101 5
b1100100 ;
b100010 !
b100010 -
b100010 %
b100010 (
b100010 0
b100010 <
1$
#370000
0$
#375000
b1100101 5
b1100100 ;
b100011 !
b100011 -
b100011 %
b100011 (
b100011 0
b100011 <
1$
#380000
0$
#385000
b1100101 5
b1100100 ;
b100100 !
b100100 -
b100100 %
b100100 (
b100100 0
b100100 <
1$
#390000
0$
#395000
b1100101 5
b1100100 ;
b100101 !
b100101 -
b100101 %
b100101 (
b100101 0
b100101 <
1$
#400000
0$
#405000
b1100101 5
b1100100 ;
b100110 !
b100110 -
b100110 %
b100110 (
b100110 0
b100110 <
1$
#410000
0$
#415000
b1100101 5
b1100100 ;
b100111 !
b100111 -
b100111 %
b100111 (
b100111 0
b100111 <
1$
#420000
0$
#425000
b1100101 5
b1100100 ;
b101000 !
b101000 -
b101000 %
b101000 (
b101000 0
b101000 <
1$
#430000
0$
#435000
b1100101 5
b1100100 ;
b101001 !
b101001 -
b101001 %
b101001 (
b101001 0
b101001 <
1$
#440000
0$
#445000
b1100101 5
b1100100 ;
b101010 !
b101010 -
b101010 %
b101010 (
b101010 0
b101010 <
1$
#450000
0$
#455000
b1100101 5
b1100100 ;
b101011 !
b101011 -
b101011 %
b101011 (
b101011 0
b101011 <
1$
#460000
0$
#465000
b1100101 5
b1100100 ;
b101100 !
b101100 -
b101100 %
b101100 (
b101100 0
b101100 <
1$
#470000
0$
#475000
b1100101 5
b1100100 ;
b101101 !
b101101 -
b101101 %
b101101 (
b101101 0
b101101 <
1$
#480000
0$
#485000
b1100101 5
b1100100 ;
b101110 !
b101110 -
b101110 %
b101110 (
b101110 0
b101110 <
1$
#490000
0$
#495000
b1100101 5
b1100100 ;
b101111 !
b101111 -
b101111 %
b101111 (
b101111 0
b101111 <
1$
#500000
0$
#505000
b1100101 5
b1100100 ;
b110000 !
b110000 -
b110000 %
b110000 (
b110000 0
b110000 <
1$
#510000
0$
#515000
b1100101 5
b1100100 ;
b110001 !
b110001 -
b110001 %
b110001 (
b110001 0
b110001 <
1$
#520000
0$
#525000
b1100101 5
b1100100 ;
b110010 !
b110010 -
b110010 %
b110010 (
b110010 0
b110010 <
1$
#530000
0$
#535000
b1100101 5
b1100100 ;
b110011 !
b110011 -
b110011 %
b110011 (
b110011 0
b110011 <
1$
#540000
0$
#545000
b1100101 5
b1100100 ;
b110100 !
b110100 -
b110100 %
b110100 (
b110100 0
b110100 <
1$
#550000
0$
#555000
b1100101 5
b1100100 ;
b110101 !
b110101 -
b110101 %
b110101 (
b110101 0
b110101 <
1$
#560000
0$
#565000
b1100101 5
b1100100 ;
b110110 !
b110110 -
b110110 %
b110110 (
b110110 0
b110110 <
1$
#570000
0$
#575000
b1100101 5
b1100100 ;
b110111 !
b110111 -
b110111 %
b110111 (
b110111 0
b110111 <
1$
#580000
0$
#585000
b1100101 5
b1100100 ;
b111000 !
b111000 -
b111000 %
b111000 (
b111000 0
b111000 <
1$
#590000
0$
#595000
b1100101 5
b1100100 ;
b111001 !
b111001 -
b111001 %
b111001 (
b111001 0
b111001 <
1$
#600000
0$
#605000
b1100101 5
b1100100 ;
b111010 !
b111010 -
b111010 %
b111010 (
b111010 0
b111010 <
1$
#610000
0$
#615000
b1100101 5
b1100100 ;
b111011 !
b111011 -
b111011 %
b111011 (
b111011 0
b111011 <
1$
#620000
0$
#625000
b1100101 5
b1100100 ;
b111100 !
b111100 -
b111100 %
b111100 (
b111100 0
b111100 <
1$
#630000
0$
#635000
b1100101 5
b1100100 ;
b111101 !
b111101 -
b111101 %
b111101 (
b111101 0
b111101 <
1$
#640000
0$
#645000
b1100101 5
b1100100 ;
b111110 !
b111110 -
b111110 %
b111110 (
b111110 0
b111110 <
1$
#650000
0$
#655000
b1100101 5
b1100100 ;
b111111 !
b111111 -
b111111 %
b111111 (
b111111 0
b111111 <
1$
#660000
0$
#665000
b1100101 5
b1100100 ;
b1000000 !
b1000000 -
b1000000 %
b1000000 (
b1000000 0
b1000000 <
1$
#670000
0$
#675000
b1100101 5
b1100100 ;
b1000001 !
b1000001 -
b1000001 %
b1000001 (
b1000001 0
b1000001 <
1$
#680000
0$
#685000
b1100101 5
b1100100 ;
b1000010 !
b1000010 -
b1000010 %
b1000010 (
b1000010 0
b1000010 <
1$
#690000
0$
#695000
b1100101 5
b1100100 ;
b1000011 !
b1000011 -
b1000011 %
b1000011 (
b1000011 0
b1000011 <
1$
#700000
0$
#705000
b1100101 5
b1100100 ;
b1000100 !
b1000100 -
b1000100 %
b1000100 (
b1000100 0
b1000100 <
1$
#710000
0$
#715000
b1100101 5
b1100100 ;
b1000101 !
b1000101 -
b1000101 %
b1000101 (
b1000101 0
b1000101 <
1$
#720000
0$
#725000
b1100101 5
b1100100 ;
b1000110 !
b1000110 -
b1000110 %
b1000110 (
b1000110 0
b1000110 <
1$
#730000
0$
#735000
b1100101 5
b1100100 ;
b1000111 !
b1000111 -
b1000111 %
b1000111 (
b1000111 0
b1000111 <
1$
#740000
0$
#745000
b1100101 5
b1100100 ;
b1001000 !
b1001000 -
b1001000 %
b1001000 (
b1001000 0
b1001000 <
1$
#750000
0$
#755000
b1100101 5
b1100100 ;
b1001001 !
b1001001 -
b1001001 %
b1001001 (
b1001001 0
b1001001 <
1$
#760000
0$
#765000
b1100101 5
b1100100 ;
b1001010 !
b1001010 -
b1001010 %
b1001010 (
b1001010 0
b1001010 <
1$
#770000
0$
#775000
b1100101 5
b1100100 ;
b1001011 !
b1001011 -
b1001011 %
b1001011 (
b1001011 0
b1001011 <
1$
#780000
0$
#785000
b1100101 5
b1100100 ;
b1001100 !
b1001100 -
b1001100 %
b1001100 (
b1001100 0
b1001100 <
1$
#790000
0$
#795000
b1100101 5
b1100100 ;
b1001101 !
b1001101 -
b1001101 %
b1001101 (
b1001101 0
b1001101 <
1$
#800000
0$
#805000
b1100101 5
b1100100 ;
b1001110 !
b1001110 -
b1001110 %
b1001110 (
b1001110 0
b1001110 <
1$
#810000
0$
#815000
b1100101 5
b1100100 ;
b1001111 !
b1001111 -
b1001111 %
b1001111 (
b1001111 0
b1001111 <
1$
#820000
0$
#825000
b1100101 5
b1100100 ;
b1010000 !
b1010000 -
b1010000 %
b1010000 (
b1010000 0
b1010000 <
1$
#830000
0$
#835000
b1100101 5
b1100100 ;
b1010001 !
b1010001 -
b1010001 %
b1010001 (
b1010001 0
b1010001 <
1$
#840000
0$
#845000
b1100101 5
b1100100 ;
b1010010 !
b1010010 -
b1010010 %
b1010010 (
b1010010 0
b1010010 <
1$
#850000
0$
#855000
b1100101 5
b1100100 ;
b1010011 !
b1010011 -
b1010011 %
b1010011 (
b1010011 0
b1010011 <
1$
#860000
0$
#865000
b1100101 5
b1100100 ;
b1010100 !
b1010100 -
b1010100 %
b1010100 (
b1010100 0
b1010100 <
1$
#870000
0$
#875000
b1100101 5
b1100100 ;
b1010101 !
b1010101 -
b1010101 %
b1010101 (
b1010101 0
b1010101 <
1$
#880000
0$
#885000
b1100101 5
b1100100 ;
b1010110 !
b1010110 -
b1010110 %
b1010110 (
b1010110 0
b1010110 <
1$
#890000
0$
#895000
b1100101 5
b1100100 ;
b1010111 !
b1010111 -
b1010111 %
b1010111 (
b1010111 0
b1010111 <
1$
#900000
0$
#905000
b1100101 5
b1100100 ;
b1011000 !
b1011000 -
b1011000 %
b1011000 (
b1011000 0
b1011000 <
1$
#910000
0$
#915000
b1100101 5
b1100100 ;
b1011001 !
b1011001 -
b1011001 %
b1011001 (
b1011001 0
b1011001 <
1$
#920000
0$
#925000
b1100101 5
b1100100 ;
b1011010 !
b1011010 -
b1011010 %
b1011010 (
b1011010 0
b1011010 <
1$
#930000
0$
#935000
b1100101 5
b1100100 ;
b1011011 !
b1011011 -
b1011011 %
b1011011 (
b1011011 0
b1011011 <
1$
#940000
0$
#945000
b1100101 5
b1100100 ;
b1011100 !
b1011100 -
b1011100 %
b1011100 (
b1011100 0
b1011100 <
1$
#950000
0$
#955000
b1100101 5
b1100100 ;
b1011101 !
b1011101 -
b1011101 %
b1011101 (
b1011101 0
b1011101 <
1$
#960000
0$
#965000
b1100101 5
b1100100 ;
b1011110 !
b1011110 -
b1011110 %
b1011110 (
b1011110 0
b1011110 <
1$
#970000
0$
#975000
b1100101 5
b1100100 ;
b1011111 !
b1011111 -
b1011111 %
b1011111 (
b1011111 0
b1011111 <
1$
#980000
0$
#985000
b1100101 5
b1100100 ;
b1100000 !
b1100000 -
b1100000 %
b1100000 (
b1100000 0
b1100000 <
1$
#990000
0$
#995000
b1100101 5
b1100100 ;
b1100001 !
b1100001 -
b1100001 %
b1100001 (
b1100001 0
b1100001 <
1$
#1000000
0$
#1005000
b1100101 5
b1100100 ;
b1100010 !
b1100010 -
b1100010 %
b1100010 (
b1100010 0
b1100010 <
1$
#1010000
0$
#1015000
b1100101 5
b1100100 ;
b1100011 !
b1100011 -
b1100011 %
b1100011 (
b1100011 0
b1100011 <
1$
#1020000
0$
#1025000
b1100101 5
b1100100 ;
b1100100 !
b1100100 -
b1100100 %
b1100100 (
b1100100 0
b1100100 <
1$
#1030000
0$
#1035000
b1 "
b1 ,
b1 )
b1 1
b1 6
b1100101 5
b1100100 ;
b1100101 !
b1100101 -
b1100101 %
b1100101 (
b1100101 0
b1100101 <
1$
#1040000
0$
#1045000
b10 "
b10 ,
b10 )
b10 1
b10 6
b1100101 5
b1100100 ;
b1100110 !
b1100110 -
b1100110 %
b1100110 (
b1100110 0
b1100110 <
1$
#1050000
0$
#1055000
b11 "
b11 ,
b11 )
b11 1
b11 6
b1100101 5
b1100100 ;
b1100111 !
b1100111 -
b1100111 %
b1100111 (
b1100111 0
b1100111 <
1$
#1060000
0$
#1065000
b100 "
b100 ,
b100 )
b100 1
b100 6
b1100101 5
b1100100 ;
b1101000 !
b1101000 -
b1101000 %
b1101000 (
b1101000 0
b1101000 <
1$
#1070000
0$
#1075000
b101 "
b101 ,
b101 )
b101 1
b101 6
b1100101 5
b1100100 ;
b1101001 !
b1101001 -
b1101001 %
b1101001 (
b1101001 0
b1101001 <
1$
#1080000
0$
#1085000
b110 "
b110 ,
b110 )
b110 1
b110 6
b1100101 5
b1100100 ;
b1101010 !
b1101010 -
b1101010 %
b1101010 (
b1101010 0
b1101010 <
1$
#1090000
0$
#1095000
b111 "
b111 ,
b111 )
b111 1
b111 6
b1100101 5
b1100100 ;
b1101011 !
b1101011 -
b1101011 %
b1101011 (
b1101011 0
b1101011 <
1$
#1100000
0$
#1105000
b1000 "
b1000 ,
b1000 )
b1000 1
b1000 6
b1100101 5
b1100100 ;
b1101100 !
b1101100 -
b1101100 %
b1101100 (
b1101100 0
b1101100 <
1$
#1110000
0$
#1115000
b1001 "
b1001 ,
b1001 )
b1001 1
b1001 6
b1100101 5
b1100100 ;
b1101101 !
b1101101 -
b1101101 %
b1101101 (
b1101101 0
b1101101 <
1$
#1120000
0$
#1125000
b1010 "
b1010 ,
b1010 )
b1010 1
b1010 6
b1100101 5
b1100100 ;
b1101110 !
b1101110 -
b1101110 %
b1101110 (
b1101110 0
b1101110 <
1$
#1130000
0$
#1135000
b1011 "
b1011 ,
b1011 )
b1011 1
b1011 6
b1100101 5
b1100100 ;
b1101111 !
b1101111 -
b1101111 %
b1101111 (
b1101111 0
b1101111 <
1$
#1140000
0$
#1145000
b1100 "
b1100 ,
b1100 )
b1100 1
b1100 6
b1100101 5
b1100100 ;
b1110000 !
b1110000 -
b1110000 %
b1110000 (
b1110000 0
b1110000 <
1$
#1150000
0$
#1155000
b1101 "
b1101 ,
b1101 )
b1101 1
b1101 6
b1100101 5
b1100100 ;
b1110001 !
b1110001 -
b1110001 %
b1110001 (
b1110001 0
b1110001 <
1$
#1160000
0$
#1165000
b1110 "
b1110 ,
b1110 )
b1110 1
b1110 6
b1100101 5
b1100100 ;
b1110010 !
b1110010 -
b1110010 %
b1110010 (
b1110010 0
b1110010 <
1$
#1170000
0$
#1175000
b1111 "
b1111 ,
b1111 )
b1111 1
b1111 6
b1100101 5
b1100100 ;
b1110011 !
b1110011 -
b1110011 %
b1110011 (
b1110011 0
b1110011 <
1$
#1180000
0$
#1185000
b10000 "
b10000 ,
b10000 )
b10000 1
b10000 6
b1100101 5
b1100100 ;
b1110100 !
b1110100 -
b1110100 %
b1110100 (
b1110100 0
b1110100 <
1$
#1190000
0$
#1195000
b10001 "
b10001 ,
b10001 )
b10001 1
b10001 6
b1100101 5
b1100100 ;
b1110101 !
b1110101 -
b1110101 %
b1110101 (
b1110101 0
b1110101 <
1$
#1200000
0$
#1205000
b10010 "
b10010 ,
b10010 )
b10010 1
b10010 6
b1100101 5
b1100100 ;
b1110110 !
b1110110 -
b1110110 %
b1110110 (
b1110110 0
b1110110 <
1$
#1210000
0$
#1215000
b10011 "
b10011 ,
b10011 )
b10011 1
b10011 6
b1100101 5
b1100100 ;
b1110111 !
b1110111 -
b1110111 %
b1110111 (
b1110111 0
b1110111 <
1$
#1220000
0$
#1225000
b10100 "
b10100 ,
b10100 )
b10100 1
b10100 6
b1100101 5
b1100100 ;
b1111000 !
b1111000 -
b1111000 %
b1111000 (
b1111000 0
b1111000 <
1$
#1230000
0$
#1235000
b10101 "
b10101 ,
b10101 )
b10101 1
b10101 6
b1100101 5
b1100100 ;
b1111001 !
b1111001 -
b1111001 %
b1111001 (
b1111001 0
b1111001 <
1$
#1240000
0$
#1245000
b10110 "
b10110 ,
b10110 )
b10110 1
b10110 6
b1100101 5
b1100100 ;
b1111010 !
b1111010 -
b1111010 %
b1111010 (
b1111010 0
b1111010 <
1$
#1250000
0$
#1255000
b10111 "
b10111 ,
b10111 )
b10111 1
b10111 6
b1100101 5
b1100100 ;
b1111011 !
b1111011 -
b1111011 %
b1111011 (
b1111011 0
b1111011 <
1$
#1260000
0$
#1265000
b11000 "
b11000 ,
b11000 )
b11000 1
b11000 6
b1100101 5
b1100100 ;
b1111100 !
b1111100 -
b1111100 %
b1111100 (
b1111100 0
b1111100 <
1$
#1270000
0$
#1275000
b11001 "
b11001 ,
b11001 )
b11001 1
b11001 6
b1100101 5
b1100100 ;
b1111101 !
b1111101 -
b1111101 %
b1111101 (
b1111101 0
b1111101 <
1$
#1280000
0$
#1285000
b11010 "
b11010 ,
b11010 )
b11010 1
b11010 6
b1100101 5
b1100100 ;
b1111110 !
b1111110 -
b1111110 %
b1111110 (
b1111110 0
b1111110 <
1$
#1290000
0$
#1295000
b11011 "
b11011 ,
b11011 )
b11011 1
b11011 6
b1100101 5
b1100100 ;
b1111111 !
b1111111 -
b1111111 %
b1111111 (
b1111111 0
b1111111 <
1$
#1300000
0$
#1305000
b11100 "
b11100 ,
b11100 )
b11100 1
b11100 6
b1100101 5
b1100100 ;
b10000000 !
b10000000 -
b10000000 %
b10000000 (
b10000000 0
b10000000 <
1$
#1310000
0$
#1315000
b11101 "
b11101 ,
b11101 )
b11101 1
b11101 6
b1100101 5
b1100100 ;
b10000001 !
b10000001 -
b10000001 %
b10000001 (
b10000001 0
b10000001 <
1$
#1320000
0$
#1325000
b11110 "
b11110 ,
b11110 )
b11110 1
b11110 6
b1100101 5
b1100100 ;
b10000010 !
b10000010 -
b10000010 %
b10000010 (
b10000010 0
b10000010 <
1$
#1330000
0$
#1335000
b11111 "
b11111 ,
b11111 )
b11111 1
b11111 6
b1100101 5
b1100100 ;
b10000011 !
b10000011 -
b10000011 %
b10000011 (
b10000011 0
b10000011 <
1$
#1340000
0$
#1345000
b100000 "
b100000 ,
b100000 )
b100000 1
b100000 6
b1100101 5
b1100100 ;
b10000100 !
b10000100 -
b10000100 %
b10000100 (
b10000100 0
b10000100 <
1$
#1350000
0$
#1355000
b100001 "
b100001 ,
b100001 )
b100001 1
b100001 6
b1100101 5
b1100100 ;
b10000101 !
b10000101 -
b10000101 %
b10000101 (
b10000101 0
b10000101 <
1$
#1360000
0$
#1365000
b100010 "
b100010 ,
b100010 )
b100010 1
b100010 6
b1100101 5
b1100100 ;
b10000110 !
b10000110 -
b10000110 %
b10000110 (
b10000110 0
b10000110 <
1$
#1370000
0$
#1375000
b100011 "
b100011 ,
b100011 )
b100011 1
b100011 6
b1100101 5
b1100100 ;
b10000111 !
b10000111 -
b10000111 %
b10000111 (
b10000111 0
b10000111 <
1$
#1380000
0$
#1385000
b100100 "
b100100 ,
b100100 )
b100100 1
b100100 6
b1100101 5
b1100100 ;
b10001000 !
b10001000 -
b10001000 %
b10001000 (
b10001000 0
b10001000 <
1$
#1390000
0$
#1395000
b100101 "
b100101 ,
b100101 )
b100101 1
b100101 6
b1100101 5
b1100100 ;
b10001001 !
b10001001 -
b10001001 %
b10001001 (
b10001001 0
b10001001 <
1$
#1400000
0$
#1405000
b100110 "
b100110 ,
b100110 )
b100110 1
b100110 6
b1100101 5
b1100100 ;
b10001010 !
b10001010 -
b10001010 %
b10001010 (
b10001010 0
b10001010 <
1$
#1410000
0$
#1415000
b100111 "
b100111 ,
b100111 )
b100111 1
b100111 6
b1100101 5
b1100100 ;
b10001011 !
b10001011 -
b10001011 %
b10001011 (
b10001011 0
b10001011 <
1$
#1420000
0$
#1425000
b101000 "
b101000 ,
b101000 )
b101000 1
b101000 6
b1100101 5
b1100100 ;
b10001100 !
b10001100 -
b10001100 %
b10001100 (
b10001100 0
b10001100 <
1$
#1430000
0$
#1435000
b101001 "
b101001 ,
b101001 )
b101001 1
b101001 6
b1100101 5
b1100100 ;
b10001101 !
b10001101 -
b10001101 %
b10001101 (
b10001101 0
b10001101 <
1$
#1440000
0$
#1445000
b101010 "
b101010 ,
b101010 )
b101010 1
b101010 6
b1100101 5
b1100100 ;
b10001110 !
b10001110 -
b10001110 %
b10001110 (
b10001110 0
b10001110 <
1$
#1450000
0$
#1455000
b101011 "
b101011 ,
b101011 )
b101011 1
b101011 6
b1100101 5
b1100100 ;
b10001111 !
b10001111 -
b10001111 %
b10001111 (
b10001111 0
b10001111 <
1$
#1460000
0$
#1465000
b101100 "
b101100 ,
b101100 )
b101100 1
b101100 6
b1100101 5
b1100100 ;
b10010000 !
b10010000 -
b10010000 %
b10010000 (
b10010000 0
b10010000 <
1$
#1470000
0$
#1475000
b101101 "
b101101 ,
b101101 )
b101101 1
b101101 6
b1100101 5
b1100100 ;
b10010001 !
b10010001 -
b10010001 %
b10010001 (
b10010001 0
b10010001 <
1$
#1480000
0$
#1485000
b101110 "
b101110 ,
b101110 )
b101110 1
b101110 6
b1100101 5
b1100100 ;
b10010010 !
b10010010 -
b10010010 %
b10010010 (
b10010010 0
b10010010 <
1$
#1490000
0$
#1495000
b101111 "
b101111 ,
b101111 )
b101111 1
b101111 6
b1100101 5
b1100100 ;
b10010011 !
b10010011 -
b10010011 %
b10010011 (
b10010011 0
b10010011 <
1$
#1500000
0$
#1505000
b110000 "
b110000 ,
b110000 )
b110000 1
b110000 6
b1100101 5
b1100100 ;
b10010100 !
b10010100 -
b10010100 %
b10010100 (
b10010100 0
b10010100 <
1$
#1510000
0$
#1515000
b110001 "
b110001 ,
b110001 )
b110001 1
b110001 6
b1100101 5
b1100100 ;
b10010101 !
b10010101 -
b10010101 %
b10010101 (
b10010101 0
b10010101 <
1$
#1520000
0$
#1525000
b110010 "
b110010 ,
b110010 )
b110010 1
b110010 6
b1100101 5
b1100100 ;
b10010110 !
b10010110 -
b10010110 %
b10010110 (
b10010110 0
b10010110 <
1$
#1530000
0$
#1535000
b110011 "
b110011 ,
b110011 )
b110011 1
b110011 6
b1100101 5
b1100100 ;
b10010111 !
b10010111 -
b10010111 %
b10010111 (
b10010111 0
b10010111 <
1$
#1540000
0$
#1545000
b110100 "
b110100 ,
b110100 )
b110100 1
b110100 6
b1100101 5
b1100100 ;
b10011000 !
b10011000 -
b10011000 %
b10011000 (
b10011000 0
b10011000 <
1$
#1550000
0$
#1555000
b110101 "
b110101 ,
b110101 )
b110101 1
b110101 6
b1100101 5
b1100100 ;
b10011001 !
b10011001 -
b10011001 %
b10011001 (
b10011001 0
b10011001 <
1$
#1560000
0$
#1565000
b110110 "
b110110 ,
b110110 )
b110110 1
b110110 6
b1100101 5
b1100100 ;
b10011010 !
b10011010 -
b10011010 %
b10011010 (
b10011010 0
b10011010 <
1$
#1570000
0$
#1575000
b110111 "
b110111 ,
b110111 )
b110111 1
b110111 6
b1100101 5
b1100100 ;
b10011011 !
b10011011 -
b10011011 %
b10011011 (
b10011011 0
b10011011 <
1$
#1580000
0$
#1585000
b111000 "
b111000 ,
b111000 )
b111000 1
b111000 6
b1100101 5
b1100100 ;
b10011100 !
b10011100 -
b10011100 %
b10011100 (
b10011100 0
b10011100 <
1$
#1590000
0$
#1595000
b111001 "
b111001 ,
b111001 )
b111001 1
b111001 6
b1100101 5
b1100100 ;
b10011101 !
b10011101 -
b10011101 %
b10011101 (
b10011101 0
b10011101 <
1$
#1600000
0$
